{
    "version": {
        "date": "2025-06-08 19:05:00",
        "plugin": "infohub_debug",
        "data_checksum": "3fa25f0c79826e74e9c04bcb4cae91d9",
        "language": "nl",
        "language_name": "Dutch",
        "language_name_local": "Nederlands",
        "country": "",
        "country_name": "",
        "file_type": "translate_file",
        "has_manual_translations": "false"
    },
    "launcher": {
        "title": "Debugprogramma",
        "description": "Gereedschap voor ontwikkelaars en testers."
    },
    "data": {
        "infohub_debug": {
            "DONE_CLEARING_CACHE_KEY": "Gereed om cache op te ruimen",
            "DONE_REFRESHING_PAGE_KEY": "Vernieuwingspagina voltooid",
            "RELOAD_PAGE._KEY": "Pagina herladen.",
            "CLEAN_OUT_OLD_PLUGINS_MARKED_BY_THE_SERVER._RELOAD_PAGE._KEY": "Oude plugins opruimen die door de server zijn gemarkeerd. Pagina herladen.",
            "CLEAN_OUT_ALL_LOCAL_PLUGINS,_RELOAD_PAGE._KEY": "Verwijder alle lokale plugins, herlaad pagina.",
            "CLEAN_OUT_ALL_LOCAL_DATA,_RELOAD_PAGE._KEY": "Verwijder alle lokale gegevens, herlaad pagina.",
            "INSTRUCTIONS_KEY": "Instructies",
            "CLICK_ON_AN_OPTION_OR_USE_THE_KEYBOARD._THESE_KEYS_ALWAYS_WORKS_WHEREVER_YOU_ARE_IN_INFOHUB._KEY": "Klik op een optie of gebruik het toetsenbord. Deze sleutels werken altijd waar je ook bent in infohub.",
            "INFORMATION_KEY": "Informatie",
            "IS_ALSO_AT_THE_BOTTOM_OF_THE_LAUNCHER_SCREEN_AS_A_BUTTON_IN_CASE_YOU_CAN_NOT_START_DEBUG_AND_HAVE_NO_KEYBOARD_ON_YOUR_DEVICE._KEY": "Is ook aan de onderkant van het launcher scherm als een knop in het geval u niet kunt starten debug en geen toetsenbord op uw apparaat.",
            "IS_THE_ONLY_OPTION_THAT_ALSO_REMOVE_ICONS_AND_TRANSLATIONS_AND_SETTINGS_FROM_THE_LOCAL_STORAGE._KEY": "Is de enige optie die ook pictogrammen en vertalingen en instellingen uit de lokale opslag verwijderen.",
            "SILENTLY_DELETE_THE_RENDER_CACHE_FOR_THE_LOGGED_IN_USER_KEY": "Stil de render cache voor de ingelogde gebruiker verwijderen",
            "LOGS_YOU_OUT_AND_REFRESH_THE_PAGE_KEY": "Logt u uit en verfrist de pagina"
        }
    }
}