{
    "version": {
        "date": "2025-06-08 18:01:58",
        "plugin": "infohub_trigger",
        "data_checksum": "519edda090d5203e179aab96be87e894",
        "language": "fr",
        "language_name": "French",
        "language_name_local": "Français",
        "country": "",
        "country_name": "",
        "file_type": "translate_file",
        "has_manual_translations": "false"
    },
    "launcher": {
        "title": "Envoyer un message personnalisé",
        "description": "En tant que développeur, vous pouvez envoyer des messages à vos fonctions."
    },
    "data": {
        "infohub_trigger": {
            "TRIGGER_KEY": "Déclencheur",
            "YOU_AS_A_DEVELOPER_CAN_SEND_A_MESSAGE_TO_YOUR_EMERGING_PLUGIN._KEY": "Vous en tant que développeur pouvez envoyer un message à votre plugin émergent.",
            "REFRESH_DATA_KEY": "Actualisation des données",
            "NODE_KEY": "Noeud",
            "SELECT_THE_NODE_YOU_WANT_TO_SEND_THE_MESSAGE_TO_KEY": "Sélectionnez le nœud que vous souhaitez envoyer le message à",
            "CLIENT_KEY": "Client",
            "SERVER_KEY": "Serveur",
            "PLUGIN_KEY": "Greffon",
            "SELECT_THE_PLUGIN_YOU_WANT_TO_SEND_THE_MESSAGE_TO_KEY": "Sélectionnez le plugin que vous souhaitez envoyer le message à",
            "FUNCTION_KEY": "Fonction",
            "SELECT_THE_FUNCTION_YOU_WANT_TO_SEND_THE_MESSAGE_TO_KEY": "Sélectionnez la fonction que vous souhaitez envoyer le message à",
            "DEFAULT_MESSAGE_FOR_THE_SELECTED_FUNCTION_KEY": "Message par défaut pour la fonction sélectionnée",
            "MESSAGE_KEY": "Message",
            "THIS_IS_THE_MESSAGE_YOU_CAN_SEND_TO_THE_SELECTED_PLUGIN._KEY": "C'est le message que vous pouvez envoyer au plugin sélectionné.",
            "THE_MESSAGE_YOU_SEE_IS_THE_DEFAULT_VALUES_THE_FUNCTION_HAVE_SET._KEY": "Le message que vous voyez est les valeurs par défaut que la fonction a définies.",
            "GET_ALL_KEY": "Tout récupérer",
            "BARE_BONE_KEY": "Ossements",
            "GET_DEFAULT_MESSAGE_KEY": "Obtenez le message par défaut",
            "SEND_MESSAGE_KEY": "Envoyer un message",
            "RESPONSE_FROM_THE_FUNCTION_KEY": "Réponse de la fonction",
            "RESPONSE_KEY": "Réponse",
            "HERE_YOU_WILL_SEE_THE_RESPONSE_FROM_THE_FUNCTION._KEY": "Ici vous verrez la réponse de la fonction.",
            "NO_CONFIG_KEY": "Pas de configuration"
        }
    }
}