{
    "version": {
        "date": "2025-06-08 19:15:45",
        "plugin": "infohub_demo",
        "data_checksum": "127658befbb13fcfe745d51fb41470f2",
        "language": "sq",
        "language_name": "Albanian",
        "language_name_local": "Shqip",
        "country": "",
        "country_name": "",
        "file_type": "translate_file",
        "has_manual_translations": "false"
    },
    "launcher": {
        "title": "Demonstrim",
        "description": "Shembuj demonstrimi. Mund t'i përdorni këto karakteristika në InfoHub"
    },
    "data": {
        "infohub_demo": {
            "INSTRUCTIONS_KEY": "Udhëzime",
            "USE_THE_MENU._KEY": "Përdor menunë.",
            "THIS_LINK_WORKS_AND_GOES_TO_INFOHUB_DEMO_->_EVENT_MESSAGE._KEY": "Kjo lidhje funksionon dhe shkon tek mesazhi i eventit ->.",
            "THIS_BUTTON_WORKS_AND_GOES_TO_INFOHUB_DEMO_->_EVENT_MESSAGE._KEY": "Ky buton funksionon dhe shkon tek mesazhi i eventit ->.",
            "THIS_SUBMIT_BUTTON_WORKS_AND_GOES_TO_INFOHUB_DEMO_->_EVENT_MESSAGE._KEY": "Ky buton funksionon dhe shkon tek mesazhi i eventit ->.",
            "THIS_ONLY_HAPPENS_IF_ALL_DATA_IS_VALID._KEY": "Kjo ndodh vetëm nëse të gjitha të dhënat janë të vlefshme."
        },
        "infohub_demo_advancedlist": {
            "CLOTHES_KEY": "Rrobat",
            "FOOT_KEY": "Fundi",
            "SOCKS_KEY": "Socks",
            "LEG_KEY": "Këmba",
            "JEANS_KEY": "Xhins",
            "BODY_KEY": "Trupi",
            "T-SHIRT_KEY": "Bluzë",
            "JACKET_KEY": "Xhaket",
            "HAND_KEY": "Dora",
            "MITTENS_KEY": "Mitens",
            "HEAD_KEY": "Lexo",
            "HAT_KEY": "Kapele",
            "HELMET_KEY": "Helmet",
            "HOCKEY_KEY": "Hockey",
            "BICYCLE_KEY": "Bicikli",
            "NAVIGATION_KEY": "Lundrimi",
            "THIS_IS_AN_EXAMPLE_OF_AN_ADVANCED_LIST._KEY": "Ky është një shembull i një liste të përparuar.",
            "YOU_CAN_EXPAND_THE_NODES_AND_CLICK_ON_THE_LABELS._KEY": "Mund të zgjeroni nyjet dhe të klikoni në etiketa.",
            "VIEW_KEY": "Shfaq",
            "VIEWING_AREA_KEY": "Duke shfaqur zonën"
        },
        "infohub_demo_audio": {
            "WELCOME_TO_INFOHUB_DEMO_AUDIO_KEY": "Mirësevini tek audio infohubug",
            "HERE_ARE_SOME_DEMOS_TO_SHOW_YOU_WHAT_INFOHUB_CAN_DO_WITH_AUDIO._KEY": "Ja disa demostrime për t'ju treguar se çfarë mund të bëjë infohubi me audio.",
            "INFOHUB_CLIENT_DO_NOT_USE_3RD_PARTY_SERVICES._KEY": "Klienti Infohub nuk përdor shërbimet e treta të partisë.",
            "ALL_DATA_MUST_COME_FROM_THE_SERVER_KEY": "Të gjitha të dhënat duhet të vijnë nga serveri",
            "THIS_IS_A_%S_KEY": "Është a",
            "%S_IS_A_3RD_PARTY_AUDIO_STREAMING_SERVICE._KEY": "%s është një shërbim regjistrimi audio i partisë së tretë.",
            "IN_NEW_TAB_KEY": "Në një skedë të re"
        },
        "infohub_demo_batch": {
            "DEMO_BATCH_KEY": "Demogroup",
            "THREE_MESSAGES_WILL_BE_SENT_TO_GET_HUB_ID_KEY": "Tre mesazhe do të dërgohen për të marrë id",
            "THE_LAST_MESSAGE_WILL_RETURN_THEM_ALL_KEY": "Mesazhi i fundit do t'i kthejë të gjithë",
            "THAT_IS_HOW_A_BATCH_CALL_WORKS_KEY": "Kështu funksionon një grup telefonatash",
            "BATCH_DEMO_ON_SERVER_KEY": "Tag në server",
            "BATCH_DEMO_ON_SERVER_CUSTOM_CODE_KEY": "Tag në server kodi",
            "START_BATCH_DEMO_ON_SERVER_KEY": "Fillo ora server",
            "THE_RESPONSE_WILL_SHOW_HERE_KEY": "Përgjigja do të shfaqet këtu",
            "BATCH_DEMO_ON_CLIENT_KEY": "Batch demo mbi klientin",
            "BATCH_DEMO_ON_CLIENT_CUSTOM_CODE_KEY": "Batch demo në kodin e personalizuar të klientit",
            "START_BATCH_DEMO_HERE_KEY": "Fillo ora",
            "BATCH_DEMO_ON_CLIENT_WITH_PLUGIN_KEY": "Batch demo tek klienti me plugin",
            "USE_BATCH_PLUGIN_ON_CLIENT_KEY": "Përdor plugin në",
            "BATCH_DEMO_ON_SERVER_WITH_PLUGIN_KEY": "Tag në server me",
            "USE_BATCH_PLUGIN_ON_SERVER_KEY": "Përdorimi në server",
            "BATCH_DEMO_ON_CLIENT_WITH_PLUGIN_THAT_USES_MEMORY_TO_STORE_THE_MESSAGES_KEY": "Batch demo tek klienti me plugin që përdor kujtesën për të ruajtur mesazhet",
            "USE_BATCH_PLUGIN_ON_CLIENT_IN_MEMORY_KEY": "Përdor plugin e grumbulluar tek klienti në kujtesë",
            "BATCH_DEMO_ON_SERVER_WITH_PLUGIN_THAT_USES_MEMORY_TO_STORE_THE_MESSAGES_KEY": "Batch demo në server me plugin që përdor kujtesën për të ruajtur mesazhet",
            "USE_BATCH_PLUGIN_ON_SERVER_IN_MEMORY_KEY": "Përdor plugin në server në memorje"
        },
        "infohub_demo_common": {
            "TIME_KEY": "Ora",
            "THIS_IS_A_LEGEND_KEY": "Kjo është legjendë",
            "DOES_NOT_TRACK_YOU_KEY": "Nuk të ndjek",
            "DOES_NOT_SELL_YOU_ANYTHING_KEY": "Nuk të shet asgjë",
            "THAT_IS_WHY_I_LIKE_THEM_KEY": "Prandaj më pëlqejnë",
            "COMMON_DEMO_KEY": "Përshkrimi i zakonshëm",
            "PLUGIN_INFOHUB_RENDER_COMMON_ARE_USED_IN_THIS_DEMO._KEY": "Plugin në.",
            "YOU_SEE_A_COMBINATION_OF_WHAT_RENDER_COMMON_CAN_DO._KEY": "Ju shihni një kombinim të asaj që përkthimi i zakonshëm mund të bëjë.",
            "HERE_IS_A_LIST_WHAT_PARTS_YOU_SEE_IN_THE_EXAMPLE:_KEY": "Ja një listë që e shihni në shembull:",
            "THE_FIRST_IMAGE_IS_IN_JPEG_FORMAT_700_PIXELS_WIDE_30KB._KEY": "Figura e parë është në pixels.",
            "_THE_SECOND_IMAGE_IS_IN_PNG_FORMAT_BLACK&WHITE,_240_PIXELS_WIDE_AND_17KB_AND_THEN_UPSCALED_TO_640_PIXELS_WIDE._KEY": "figura e dytë është në formatin e zi& e bardhë, 240 pixel e gjerë dhe 17kb dhe pastaj është rritur në 640 pixel të gjera.",
            "YOU_CAN_SEE_SEVERAL_THINGS_HERE:_KEY": "Ju mund të shihni disa gjëra këtu:",
            "LIST_-_BULLET_LIST_LIKE_THIS_ONE_KEY": "Lista e plumbave si ky",
            "VALUE_-_ANY_VALUE,_USED_HERE_FOR_THE_TIME_STAMP_KEY": "Vlera - çdo vlerë, e përdorur këtu për vulën e kohës",
            "IMAGE_-_THE_PHOTO_IS_AN_IMAGE,_THE_DUCK_TOO_KEY": "Fotografia - fotografia është një imazh, rosa gjithashtu",
            "LEGEND_-_A_FRAME_WITH_A_LABEL._YOU_CAN_PUT_THINGS_IN_IT_KEY": "Legjenda - një kornizë me etiketë. Mund të fusësh gjëra në të",
            "IFRAME_-_A_BOX_WITH_3RD_PARTY_CONTENTS._USE_WITH_CAUTION_KEY": "I kornizë - një kuti me përmbajtjen e partisë së tretë. Përdor me kujdes",
            "CONTAINER_-_A_SPAN,_DIV_OR_P_TAG_THAT_YOU_CAN_PUT_THINGS_IN_KEY": "Përmbanjës - një hapësirë, div ose një etiketë ku mund t'i vendosësh gjërat",
            "USE_JPEG_FOR_PHOTOGRAPHS_KEY": "Përdorimi për fotografi",
            "USE_PNG_FOR_SMALL_DETAILED_IMAGES_WHERE_YOU_CAN_NOT_USE_SVG_OR_JPEG_KEY": "Përdor png për nuk",
            "USE_A_RESOLUTION_CLOSE_TO_THE_VIEWED_RESOLUTION._DO_NOT_UPSCALE._KEY": "Përdor një rezolutë afër rezolutës që shihet. Mos u ngjit.",
            "_AVOID_DOWNSCALING_TOO_MUCH._KEY": "mos u lodh shumë.",
            "AFFECT_PROGRESS_BAR_KEY": "Ndikim në shtyllën e progresit"
        },
        "infohub_demo_document": {
            "SELECT_FILE_KEY": "Zgjidh _gjithçka",
            "LOAD_EXAMPLE_KEY": "Ngarko",
            "WRITE_YOUR_MARKDOWN_TEXT_HERE_OR_PRESS_THE_BUTTON_ABOVE_TO_SELECT_A_LOCAL_TEXT_FILE._KEY": "Shkruaj këtu tekstin e shënuar ose shtyp butonin sipër për të zgjedhur një file teksti lokal.",
            "MARKDOWN_TO_HTML_KEY": "Shënon tek html"
        },
        "infohub_demo_form": {
            "WELCOME_TO_INFOHUB_DEMO_FORM_KEY": "Mirësevini në formularin infohubug",
            "HERE_ARE_SOME_DEMOS_TO_SHOW_YOU_WHAT_INFOHUB_CAN_DO_WITH_FORMS._KEY": "Ja disa demostrime për t'ju treguar se çfarë mund të bëjë infohubi me format.",
            "A_FIELDSET_WITH_DEMO_FORM_ELEMENTS_KEY": "Një fushë me elementë demo form",
            "MY_BUTTON_KEY": "Butoni im",
            "WRITE_SOMETHING_NICE_HERE_KEY": "Shkruaj diçka të bukur këtu",
            "YOUR_MEAL_KEY": "Ushqimi juaj",
            "WHAT_DO_YOU_WANT_ON_YOUR_HAMBURGER_KEY": "Çfarë do nga hamburgeri yt",
            "BREAD_KEY": "Buka",
            "NORMAL_BREAD_KEY": "Buka normale",
            "FIBER_BREAD_KEY": "Buka e shpimit",
            "BURGER_KEY": "Burger",
            "GREEN_BURGER_KEY": "Burger jeshil",
            "BOAR_BURGER_KEY": "Buger Boar",
            "EXTRAS_KEY": "Shtesë",
            "CHEESE_KEY": "Cheese",
            "SALAD_KEY": "Salad",
            "MUSTARD_KEY": "Mustardë",
            "UNION_KEY": "Asnjë",
            "EXTRA_KEY": "Shtesë",
            "BELOW_YOU_CAN_PRESS_THE_BUTTON_TO_DOWNLOAD_A_TEXT_FILE_WITH_A_GREETING._EXAMPLE_OF_DOWNLOADING_FILES._KEY": "Poshtë mund të shtypësh butonin për të shkarkuar një file teksti me përshëndetje. Shembulli i shkarkimit të skedarëve.",
            "DOWNLOAD_FILE_KEY": "Shkarkimi i file",
            "BELOW_YOU_CAN_PRESS_THE_BUTTON_TO_GET_A_FILE_SELECTOR._KEY": "Poshtë mund të shtypësh butonin për të marrë një zgjedhës file.",
            "SELECT_ONE_OR_MORE_JPEG_IMAGES._KEY": "Zgjidh një apo më shumë figura vertikale.",
            "THEY_WILL_BE_READ_AND_SHOWN_UNDER_THE_BUTTON._KEY": "Ato do të lexohen dhe do të shfaqen nën buton.",
            "SELECT_IMAGES_KEY": "Zgjidh figurat"
        },
        "infohub_demo_form2": {
            "WELCOME_TO_THE_INFOHUB_DEMO_FOR_MORE_ADVANCED_FORMS_KEY": "Mirësevini në reklamimin për forma më të përparuara",
            "IN_THIS_DEMO_YOU_CAN_ORDER_A_MEAL_AT_A_RESTAURANT._KEY": "Në këtë demostrim mund të porosisësh një vakt në një restorant.",
            "ALL_THE_FORM_ELEMENTS_ARE_USED_IN_THIS_DEMO._KEY": "Të gjitha elementet e formës janë përdorur në këtë demostrim.",
            "YOUR_BURGER_MEAL_KEY": "Ushqimi yt",
            "PLEASE_SELECT_THE_DETAILS_FOR_YOUR_BURGER_MEAL._KEY": "Ju lutem zgjidhni detajet për ushqimin tuaj.",
            "ORDER_YOUR_MEAL_KEY": "Urdhëro ushqimin",
            "QUICK_BURGER_KEY": "Senduiç i shpejtë",
            "LUNCH_BURGER_KEY": "Dreka",
            "DINNER_BURGER_KEY": "Hamburger darkash",
            "ALIAS_KEY": "Pseudonimi",
            "YOUR_ALIAS_FOR_THIS_BURGER_ORDER,_SO_YOU_CAN_EASILY_REORDER_AT_A_LATER_TIME_KEY": "Pseudonimi juaj për këtë hamburger, kështu që ju mund të rirregulloni lehtë në një kohë të mëvonshme",
            "FRYING_THE_BURGER_KEY": "Lëpirja e hamburgerit",
            "HOW_MUCH_DU_YOU_WANT_US_TO_FRY_THE_BURGER,_FROM_LIGHTLY_TOUCHING_THE_PAN_UP_TO_METEORITE_KEY": "Sa do që të pjekim hamburgerin nga prekja e lehtë e tiganit deri në meteorit",
            "SIDE_DISH_KEY": "Ana",
            "WHAT_DO_YOU_WANT_TO_MAKE_YOUR_MEAL_EVEN_BETTER_KEY": "Çfarë do që ta bësh ushqimin më të mirë",
            "NOTHING_KEY": "Asgjë",
            "CUTLERY_KEY": "Cutlery",
            "KNIFE_KEY": "Thikë",
            "FORK_KEY": "Fork",
            "PORCELAIN_KEY": "Porcelani",
            "PLAIT_KEY": "Plait",
            "GLASS_KEY": "Syze",
            "FABRIC_KEY": "Fabric",
            "NAPKIN_KEY": "Napkin",
            "TABLE_CLOTH_KEY": "Copa tabele",
            "YOUR_SPECIAL_REQUESTS_KEY": "Kërkesat tuaja speciale",
            "SPECIAL_REQUESTS_KEY": "Kërkesa të veçanta",
            "IF_YOU_HAVE_SOME_SPECIAL_REQUESTS_FOR_YOUR_MEAL_THEN_WRITE_THEM_HERE._KEY": "Nëse keni disa kërkesa të veçanta për ushqimin tuaj atëherë shkruajini këtu.",
            "A_DATE_MEAL_KEY": "Një vakt date",
            "AN_AFTER_MOVIE_MEAL_KEY": "Një vakt pas filmit",
            "A_BEFORE_MOVIE_MEAL_KEY": "Një vakt para filmit",
            "ULTRA_RUNNING_MEAL_KEY": "Ushqim i lirë",
            "MEAL_DURING_SHOPPING_KEY": "Ushqim gjatë pazarit",
            "BREAD_KEY": "Buka",
            "WHAT_KIND_OF_BREAD_DO_YOU_WANT?_KEY": "Çfarë lloj buke do?",
            "PLAIN_BREAD_KEY": "Bukë e thjeshtë",
            "FIBER_BREAD_KEY": "Buka e shpimit",
            "SESAM_BREAD_KEY": "Buka Sezam",
            "BURGER_KEY": "Burger",
            "WHAT_KIND_OF_BURGER_DO_YOU_WANT?_KEY": "Çfarë lloj hamburgeri do?",
            "TOFU_BURGER_KEY": "Tofu hamburger",
            "HALLOUMI_BURGER_KEY": "Hallumi hamburger",
            "SOY_BURGER_KEY": "Hamburger Soy",
            "CARROT_BASED_BURGER_KEY": "Carrot hamburger me bazë",
            "BEETROOT_BASED_BURGER_KEY": "Bamer i bazuar në Beetroot",
            "BURGER_EXTRAS_KEY": "Burger",
            "EXTRAS_THAT_WE_CAN_ADD_TO_YOUR_BURGER_KEY": "Ekstra që mund t'i shtojmë hamburgerit tënd",
            "CHEESE_KEY": "Cheese",
            "SALAD_KEY": "Salad",
            "MUSTARD_KEY": "Mustardë",
            "UNION_KEY": "Asnjë",
            "PICKLES_KEY": "Piklet",
            "OF_AGE_KEY": "Nga mosha",
            "I_CAN_ONLY_SELL_TO_YOU_IF_YOU_ARE_OF_AGE_KEY": "Mund t'ju shes vetëm nëse jeni të moshës",
            "I_AM_18_YEARS_OR_OLDER_KEY": "Jam 18 vjeç",
            "FLOWER_KEY": "Fluksi",
            "YOU_GET_A_FLOWER_ON_THE_TABLE._KEY": "Ke një lule në tavolinë.",
            "SELECT_A_COLOUR_AND_WE_WILL_DO_A_CLOSE_MATCH_WITH_THE_FLOWERS_WE_HAVE._KEY": "Zgjidh një ngjyrë dhe do të bëjmë një ndeshje të ngushtë me lulet që kemi.",
            "NOTHING_SPECIAL_KEY": "Asgjë e veçantë",
            "ONLY_VEGETABLES_AND_SPICES_KEY": "Vetëm perime dhe erëza",
            "I_WANT_TO_GO_ALL_IN_WITH_THIS_DINNER._KEY": "Dua të shkoj me këtë darkë.",
            "DION_MUSTARD_AND_ROMANI_SALAD!!_KEY": "Sinapi i Dionit dhe sallata e Romës!",
            "THIS_SUBMIT_BUTTON_WORKS_AND_GOES_TO_INFOHUB_DEMO._KEY": "Ky buton do të funksionojë dhe do të shkojë në trazim.",
            "THIS_ONLY_HAPPENS_IF_ALL_DATA_IS_VALID._KEY": "Kjo ndodh vetëm nëse të gjitha të dhënat janë të vlefshme."
        },
        "infohub_demo_frog": {
            "INSTRUCTIONS_KEY": "Udhëzime",
            "RESULT_KEY": "Rezultati",
            "WHEN_YOU_DO_A_MISTAKE_IN_YOUR_RENDERING_CODE_THEN_THE_FROG_SHOWS_UP_AS_A_PLACEHOLDER._KEY": "Kur bën një gabim në kodin e përkthimit, atëherë bretkoca shfaqet si vendshënuese.",
            "HAVE_YOU_SEEN_ANY_FROGS?_KEY": "Ke parë ndonjë bretkosa?",
            "I_MADE_A_FROG_IS_A_SWEDISH_EXPRESSION_FOR_MAKING_A_MISTAKE._KEY": "Unë bëra një bretkosë është një shprehje e çuditshme për të bërë një gabim.",
            "JAG_GJORDE_EN_GRODA._KEY": "Jag quorde en groda.",
            "IF_YOU_RENDER_AN_OBJECT_WITH_AN_UNKNOWN_TYPE_OR_SUBTYPE_THEN_A_FROG_APPEAR_INSTEAD._KEY": "Nëse e bëni një objekt me një lloj të panjohur ose me nëntip, atëherë shfaqet një bretkosë.",
            "MAKE_A_FROG_KEY": "Bëni një bretkosë",
            "CORRECT_WAY_KEY": "Drejt",
            "MISTAKE_#1_-_WRONG_SUBTYPE_KEY": "Gabim",
            "MISTAKE_#2_-_WRONG_TYPE_KEY": "Gabim lloji",
            "CORRECT,_THE_FROG_IS_RENDERED_BY_CALLING_THE_RENDER_FROG_PLUGIN._KEY": "Saktë, bretkoca bëhet duke e quajtur plugin e bretkosës.",
            "MISTAKE_#1,_THE_FROG_WERE_RENDERED_BY_CALLING_RENDER_COMMON_WITH_THE_NONE_EXISTING_SUBTYPE_FIZBAZ._KEY": "Gabimi nr.1, bretkoca u bë duke e quajtur të zakonshëm me asnjë nëntip ekzistues fizbaz.",
            "THAT_GIVES_A_FROG_AND_AN_ERROR_MESSAGE_ON_TOP._KEY": "Kjo i jep një bretkocë dhe një mesazh gabimi në krye.",
            "MISTAKE_#2,_THE_FROG_WERE_RENDERED_BY_CALLING_THE_NONE_EXISTING_PLUGIN_FOOBAR._KEY": "Gabim, bretkoca u bë duke e quajtur plugin asnjë ekzistuese."
        },
        "infohub_demo_link": {
            "WELCOME_TO_INFOHUB_DEMO_LINK_KEY": "Mirësevini tek lidhja infohub demo",
            "HERE_ARE_SOME_DEMOS_TO_SHOW_YOU_WHAT_INFOHUB_CAN_DO_WITH_LINKS._KEY": "Ja disa demostrime për t'ju treguar se çfarë mund të bëjë infohubi me lidhje.",
            "A_NORMAL_EVENT_LINK_KEY": "Një lidhje normale eventi",
            "TOGGLE_THE_IMAGE_SHOW\/HIDE_KEY": "Kavo figurë",
            "MY_EXTERNAL_LINK_TO_THE_ABC_CLUB_KEY": "Lidhja ime e jashtme me klubin abc",
            "EMBEDDED_CONTENT_-_CLICK_TO_SUBSTITUTE_THIS_TEXT_KEY": "Përpunim në këtë tekst",
            "THE_EVENT_LINK_KEY": "Lidhja e ngjarjes",
            "THIS_IS_WHAT_IS_RENDERED_WHEN_YOU_PRESS_THE_EVENT_LINK._KEY": "Kjo është ajo që është përkthyer kur shtyp lidhjen e ngjarjes.",
            "EVENT_LINKS_ALWAYS_COME_TO_THE_LEVEL_1_PLUGIN_IN_FUNCTION_EVENT_MESSAGE._KEY": "Lidhjet e ngjarjeve vijnë gjithmonë në nivelin 1 të plugin në mesazhin e funksionit.",
            "FROM_THERE_YOU_CAN_DO_WHATEVER_YOU_WANT._KEY": "Që atje mund të bësh çfarë të duash.",
            "I_WANTED_TO_RENDER_THIS._KEY": "Doja ta bëja këtë."
        },
        "infohub_demo_major": {
            "PUT_A_TITLE_ON_IT_KEY": "Vendos një titull mbi të",
            "MY_CONTENT,_CLICK_TO_SEE_THE_EMBEDDED_CONTENT_KEY": "Përmbajtja ime, kliko për të parë përmbajtjen e trupëzuar",
            "MY_EMBEDDED_DATA_KEY": "Të dhënat e mia të ngulitura",
            "EMBEDS_ANOTHER_IMAGE_KEY": "Një figurë tjetër",
            "CLICK_ON_THE_IMAGE_TO_SEE_THE_EMBEDDED_IMAGE_KEY": "Kliko mbi figurën për të shikuar figurën e trupëzuar",
            "NO_LINKS,_JUST_DISPLAYS_AN_IMAGE_KEY": "Jo lidhje, vetëm shfaq një figurë",
            "MY_EXTERNAL_LINK_TO_THE_ABC_CLUB_KEY": "Lidhja ime e jashtme me klubin abc"
        },
        "infohub_demo_map": {
            "WELCOME_TO_INFOHUB_DEMO_MAP_KEY": "Mirësevini në hartën e infohubug",
            "HERE_ARE_SOME_DEMOS_TO_SHOW_YOU_WHAT_INFOHUB_CAN_DO_WITH_MAPS._KEY": "Ja disa demostrime për t'ju treguar se çfarë mund të bëjë infohubi me hartat.",
            "INFOHUB_CLIENT_DO_NOT_USE_3RD_PARTY_SERVICES._KEY": "Klienti Infohub nuk përdor shërbimet e treta të partisë.",
            "ALL_DATA_MUST_COME_FROM_THE_SERVER_KEY": "Të gjitha të dhënat duhet të vijnë nga serveri",
            "THIS_IS_A_%S_KEY": "Është a",
            "%S_IS_A_3RD_PARTY_MAP_STREAMING_SERVICE._KEY": "%s është një hartë e tretë e partisë.",
            "IN_NEW_TAB_KEY": "Në një skedë të re"
        },
        "infohub_demo_menu": {
            "DEMO_COLLECTION_KEY": "Koleksion demi",
            "TEXT_DEMO_KEY": "Përshkrimi i tekstit",
            "COMMON_OBJECTS_DEMO_KEY": "Objekte",
            "SVG_RENDERING_DEMO_KEY": "Svg",
            "YOU_GET_A_FROG_KEY": "Ju merrni një bretkosë",
            "VIDEO_STREAM_SERVICES_KEY": "Video",
            "AUDIO_STREAM_SERVICES_KEY": "Zëri",
            "MAP_SERVICES_KEY": "Shërbimet e hartave",
            "LINK_-_DIFFERENT_KINDS_KEY": "Lidhje - lloje të ndryshme",
            "PRESENTATION_BOX_KEY": "Kuti paraqitjeje",
            "PROGRESS_BAR_KEY": "Paneli i progresit",
            "ADVANCED_LIST_KEY": "Listë e detajuara",
            "TABS_LIST_KEY": "Lista e skedave",
            "FORM_-_SIMPLE_KEY": "Formular - thjeshtë",
            "FORM_-_ADVANCED_KEY": "Formular",
            "TABLE_KEY": "Tabela",
            "DOCUMENT_TEXT_KEY": "Kornizë dokumenti",
            "TIMER_KEY": "Timer",
            "STORAGE_KEY": "Arkivi",
            "STATUS_KEY": "Gjendja",
            "BATCH_KEY": "Batch"
        },
        "infohub_demo_progress": {
            "PROGRESS_BAR_DEMO_KEY": "Thjeshtë",
            "OF_KEY": "Nga",
            "PRESS_TO_START_KEY": "Shtypi nga",
            "PRESS_TO_PROGRESS_KEY": "Vazhdo"
        },
        "infohub_demo_status": {
            "DEMO_STATUS_KEY": "Gjëndja dem",
            "FILE_LOADED_KEY": "File i ngarkuar",
            "FILE_LOADED_DESCRIPTION_KEY": "Përshkrimi i ngarkuar me file",
            "FILE_NOT_LOADED_KEY": "File nuk u ngarkua",
            "FILE_NOT_LOADED_DESCRIPTION_KEY": "File nuk u ngarkua",
            "UNKNOWN_KEY": "Nuk njihet",
            "UNKNOWN_DESCRIPTION_KEY": "Përshkrimi",
            "SET_STATUS_FILE_LOADED_KEY": "Kreu i gjendjes file",
            "SET_STATUS_FILE_NOT_LOADED_KEY": "File nuk",
            "SET_STATUS_UNKNOWN_KEY": "Gjëndja nuk njihet"
        },
        "infohub_demo_storage": {
            "INFOHUB_DEMO_STORAGE_KEY": "Horizontal",
            "YOU_CAN_TEST_THE_STORAGE_ON_THE_CLIENT_AND_SERVER_KEY": "Mund të testoni depon në klient dhe server",
            "WRITE_KEY": "Shkrim",
            "SELECT_OPTIONS_AND_PRESS_BUTTON_TO_WRITE_KEY": "Zgjidh opsionet dhe shtyp pulsantin që duhet shkruar",
            "NODE_KEY": "Node",
            "CLIENT_KEY": "Klienti",
            "SERVER_KEY": "Serveri",
            "MODE_KEY": "Modaliteti",
            "OVERWRITE_KEY": "Mbishkruaj",
            "MERGE_KEY": "Bashkimi",
            "PATH_KEY": "Pozicioni",
            "A->TEST1_KEY": "A",
            "B->TEST2_KEY": "B",
            "B->TEST3_KEY": "B->test3",
            "C->TEST4_KEY": "C",
            "ALL_FOUR_KEY": "Katër",
            "B->*_KEY": "B->*",
            "DATA_KEY": "Të dhëna",
            "ADAM_KEY": "Adami",
            "BERTIL_KEY": "Bertil",
            "CESAR_KEY": "Cezari",
            "FLAG_TRUE_KEY": "Flamuri është i vërtetë",
            "FLAG_FALSE_KEY": "Flamuri është i rremë",
            "EMPTY_KEY": "Bosh",
            "READ_KEY": "Lexo",
            "SELECT_OPTIONS_AND_PRESS_BUTTON_TO_READ_KEY": "Zgjidh opsionet dhe shtyp pulsantin që duhet lexuar",
            "WANTED_DATA_KEY": "Kërkohet",
            "FIRST_NAME_KEY": "Emri",
            "LAST_NAME_KEY": "Mbiemri",
            "HERE_YOU_WILL_SEE_THE_DATA_WE_READ_FROM_STORAGE_KEY": "Këtu do të shihni të dhënat që lexojmë nga magazina",
            "READ_DATA_KEY": "Lexo të dhënat",
            "THE_DATA_READ_FROM_STORAGE._KEY": "Të dhënat lexohen nga magazina."
        },
        "infohub_demo_svg": {
            "WELCOME_TO_INFOHUB_DEMO_SVG_KEY": "Mirësevini në infohub dem svg",
            "HERE_ARE_SOME_DEMOS_TO_SHOW_YOU_WHAT_INFOHUB_CAN_DO_WITH_INFOHUB_SVG._KEY": "Ja disa demostrime për t'ju treguar se çfarë mund të bëjë infohub me svg infohub.",
            "IF_YOU_INSTEAD_WANT_TO_USE_EXISTING_SVG_FILES_THEN_HAVE_A_LOOK_AT_INFOHUB_RENDER_COMMON._KEY": "Nëse në vend të kësaj dëshironi të përdorni skedarët ekzistues svg, atëherë duhet të shikoni në infohub që është i zakonshëm.",
            "RECTANGE_KEY": "Retange",
            "A_SIMPLE_RECTANGLE_KEY": "Një drejtkëndësh i thjeshtë",
            "CIRCLE_KEY": "Rreth",
            "A_SIMPLE_CIRCLE_KEY": "Një rreth i thjeshtë",
            "SHADOW_KEY": "Hije",
            "HOW_TO_DO_SHADOWS_KEY": "Si të bësh hije"
        },
        "infohub_demo_table": {
            "ID_KEY": "Id",
            "VIEW_KEY": "Shfaq",
            "NAME_KEY": "Emri",
            "YEAR_KEY": "Viti",
            "SCORE_KEY": "Pikë",
            "E-MAIL_KEY": "Email",
            "IMAGE_KEY": "Figura",
            "THIS_IS_A_LEGEND_KEY": "Kjo është legjendë",
            "CLICKED_ROW_WITH_ID:_KEY": "Rreshti i klikuar me id:"
        },
        "infohub_demo_text": {
            "WELCOME_TO_INFOHUB_DEMO_TEXT_KEY": "Mirësevini në tekst",
            "PLUGIN_INFOHUB_RENDER_TEXT_IS_USED_IN_THIS_DEMO._YOU_CAN_USE_TEXT_TO_BIND_TOGETHER_RENDERED_OBJECTS._KEY": "Plugin është në. Mund të përdorni tekstin për të lidhur bashkë objektet e përkthyera.",
            "THE_TEXT_RENDERER_IS_THE_MOST_IMPORTANT_RENDERER_OF_THEM_ALL._KEY": "Përkthimi i tekstit është përkthimi më i rëndësishëm nga të gjithë.",
            "IT_ACTS_AS_THE_GLUE_THAT_COMBINE_TOGETHER_ALL_THE_OTHER_RENDERED_PIECES._KEY": "Ajo vepron si ngjitës që kombinon të gjitha pjesët e tjera të përkthyera.",
            "BUILT_IN_COMMANDS_KEY": "Të ndërtuara në komanda",
            "YOU_CAN_DO_THIS_KEY": "Mund ta bësh këtë",
            "YOU_CAN_ALSO_USE_KEY": "Ju gjithashtu mund të përdorni",
            "OR_A_LINE_LIKE_THIS_KEY": "Ose një vijë si kjo",
            "COLUMNS_KEY": "Kollona",
            "YOU_CAN_ACTIVATE_COLUMNS._KEY": "Mund të aktivizoni kolonat.",
            "THEN_YOU_AUTOMATICALLY_GET_COLUMNS_THAT_YOUR_TEXT_CAN_FLOW_IN._KEY": "Pastaj merrni automatikisht kollona që teksti juaj mund të rrjedhin.",
            "YOU_CAN_KEY": "Mundesh",
            "HIGHLIGHT_PORTIONS_OF_THE_TEXT_LIKE_THIS_KEY": "Vër në dukje pjesët e tekstit si ky",
            "AND_YOU_CAN_INCLUDE_OTHER_ELEMENTS_IN_YOUR_TEXT,_FOR_EXAMPLE:_KEY": "Dhe ju mund të përfshini elemente të tjera në tekstin tuaj, për shembull:",
            "ZOOM_LEVEL_KEY": "Niveli i zmadhimit",
            "YOU_CAN_ZOOM_THE_VIEW_IN_YOUR_BROWSER._KEY": "Mund ta zmadhosh pamjen në shfletuesin tënd.",
            "WHEN_YOU_DO_THAT_AND_THE_SPACE_IS_TO_NARROW_FOR_THE_COLUMN,_THEN_IT_REDUCES_THE_NUMBER_OF_COLUMNS._KEY": "Kur e bëni këtë dhe hapësira duhet ngushtuar për kolonën, pastaj redukton numrin e kollonave.",
            "YOU_ALWAYS_GET_A_READABLE_VIEW_IN_ALL_ZOOM_LEVELS._KEY": "Gjithmonë keni një pamje të lexueshme në të gjitha nivelet e zmadhimit.",
            "SECTIONS_KEY": "Pjesë",
            "YOU_SEE_THAT_THE_H2_SECTIONS_DO_NOT_WRAP_NICE_IN_THE_COLUMNS._KEY": "Ju shikoni se seksionet h2 nuk mbyllen bukur në kolona.",
            "THERE_ARE_CSS_COMMANDS_TO_FIX_THAT_IN_MOST_BROWSERS._I_HAVE_THAT_ON_MY_TODO_LIST._KEY": "Ka komanda css për të rregulluar atë në shumicën e shfletuesve. E kam në listën time.",
            "MY_EXTERNAL_LINK_TO_THE_ABC_CLUB_KEY": "Lidhja ime e jashtme me klubin abc"
        },
        "infohub_demo_timer": {
            "TIMER_DEMO_KEY": "Thjeshtë",
            "PRESS_THE_BUTTONS_TO_CHANGE_THE_COLOURS_KEY": "Shtyp pulsantët për të ndryshuar ngjyrat",
            "RED_KEY": "I kuq",
            "GREEN_KEY": "I gjelbër",
            "BLUE_KEY": "Blu",
            "ADVANCED_TIMER_DEMO_KEY": "Thjeshtë",
            "PRESS_THE_BUTTON_TO_START_THE_DEMO_KEY": "Shtyp butonin për të filluar demzimin",
            "ADVANCED_TIMER_KEY": "Avancues",
            "THE_RESULT_KEY": "Rezultati",
            "NUMBER_KEY": "Numri",
            "WAIT_KEY": "Prit",
            "SIMULATE_SENDING_KEY": "Simulo dërgimin"
        },
        "infohub_demo_video": {
            "WELCOME_TO_INFOHUB_DEMO_VIDEO_KEY": "Mirësevini në video",
            "HERE_ARE_SOME_DEMOS_TO_SHOW_YOU_WHAT_INFOHUB_CAN_DO_WITH_VIDEO._KEY": "Ja disa demostrime për t'ju treguar se çfarë mund të bëjë infohubi me videon.",
            "INFOHUB_CLIENT_DO_NOT_USE_3RD_PARTY_SERVICES._KEY": "Klienti Infohub nuk përdor shërbimet e treta të partisë.",
            "ALL_DATA_MUST_COME_FROM_THE_SERVER_KEY": "Të gjitha të dhënat duhet të vijnë nga serveri",
            "FIRST_WE_HAVE_A_YOUTUBE_PRESENTATION_BOX._KEY": "Në fillim kemi një kuti prezantimi.",
            "AND_THEN_WE_HAVE_A_VIMEO_VIDEO_KEY": "Dhe pastaj kemi një video vimeo",
            "AND_HERE_WE_HAVE_A_DAILY_MOTION_VIDEO._KEY": "Dhe këtu kemi një video të përditshme.",
            "THIS_IS_A_%S_KEY": "Është a",
            "%S_IS_A_3RD_PARTY_VIDEO_STREAMING_SERVICE._KEY": "%s është një shërbim i tretë videosh i partisë.",
            "IN_NEW_TAB_KEY": "Në një skedë të re"
        }
    }
}